rmm/__about__.py
rmm/__init__.py
rmm/__main__.py
rmm/cli.py
rmm/config.py
rmm/exception.py
rmm/manager.py
rmm/mod.py
rmm/modlist.py
rmm/modsconfig.py
rmm/multiselect.py
rmm/path.py
rmm/steam.py
rmm/util.py
rmm_awesome-1.1.3.dist-info/METADATA
rmm_awesome-1.1.3.dist-info/WHEEL
rmm_awesome-1.1.3.dist-info/entry_points.txt
rmm_awesome-1.1.3.dist-info/licenses/LICENSE
rmm_awesome-1.1.3.dist-info/RECORD
