Metadata-Version: 2.1
Name: rmm-awesome
Version: 1.1.3
Summary: A mod manager for RimWorld. Forked from rmm-spoons
Project-URL: Homepage, https://github.com/pswsm/rmm
Project-URL: Repository, https://github.com/pswsm/rmm
Author-email: Pau Figueras <github@pswsm.cat>, Michael Ciociola <michael@ciocio.la>
License-File: LICENSE
Classifier: License :: OSI Approved :: GNU General Public License v3 (GPLv3)
Classifier: Operating System :: OS Independent
Classifier: Programming Language :: Python :: 3
Classifier: Topic :: Games/Entertainment
Classifier: Topic :: System :: Archiving :: Packaging
Requires-Python: >=3.8
Requires-Dist: bs4
Requires-Dist: tabulate
